{
  "defaultCode" : "en_US",
  "defaultLabel" : "English (US)",
  "id" : "901ebd6a-994a-4af9-bf56-dbbfb6fe570c",
  "languages" : [ {
    "countryCode" : "IN",
    "fallbackLanguageId" : null,
    "id" : "dbdce6c1-103d-4e81-a9c8-f89b9f9b8fea",
    "isActive" : true,
    "label" : "English (Indian) (IN)",
    "languageCode" : "en",
    "type" : "language"
  }, {
    "countryCode" : "",
    "fallbackLanguageId" : null,
    "id" : "2896a096-22d4-47ee-8dc5-09b5623654c7",
    "isActive" : true,
    "label" : "Japanese",
    "languageCode" : "ja",
    "type" : "language"
  } ],
  "type" : "languageContainer"
}